mozsci/__init__.py
mozsci/_c_utils.so
mozsci/cross_validate.py
mozsci/ems.py
mozsci/evaluation.py
mozsci/histogram.py
mozsci/inputs.py
mozsci/map_train.py
mozsci/numpy_util.py
mozsci/pca.py
mozsci/spearmanr_by_fast.so
mozsci/variables.py
mozsci/glm/__init__.py
mozsci/glm/prob_distributions.py
mozsci/glm/regularization.py
mozsci/glm/simplified_glm.py
mozsci/models/__init__.py
mozsci/models/linear_regression.py
mozsci/models/logistic_regression.py
mozsci-0.9.2.dist-info/DESCRIPTION.rst
mozsci-0.9.2.dist-info/METADATA
mozsci-0.9.2.dist-info/metadata.json
mozsci-0.9.2.dist-info/RECORD
mozsci-0.9.2.dist-info/top_level.txt
mozsci-0.9.2.dist-info/WHEEL
