Metadata-Version: 2.0
Name: mozsci
Version: 0.9.2
Summary: Data science tools from Moz
Home-page: http://github.com/seomoz/mozsci
Author: Moz Data Science
Author-email: science@moz.com
License: MIT
Platform: Posix; MacOS X
Classifier: License :: OSI Approved :: MIT License
Classifier: Development Status :: 4 - Beta
Classifier: Intended Audience :: Developers
Classifier: Topic :: Scientific/Engineering
Classifier: Topic :: Scientific/Engineering :: Artificial Intelligence
Classifier: Intended Audience :: Science/Research
Classifier: Programming Language :: Python :: 2
Classifier: Programming Language :: Python :: 2.7
Classifier: Programming Language :: Python :: 3
Classifier: Programming Language :: Python :: 3.3
Classifier: Programming Language :: Python :: 3.4
Requires-Dist: numpy
Requires-Dist: scipy
Requires-Dist: nose
Requires-Dist: coverage
Requires-Dist: Cython (>=0.17)
Requires-Dist: simplejson
Requires-Dist: scikit-learn
Requires-Dist: six
